dframcy/__init__.py
dframcy/cli.py
dframcy/dframcy.py
dframcy/matcher.py
dframcy/utils.py
tests/__init__.py
tests/test_dframcy.py
tests/test_matcher.py
dframcy-0.1.6.dist-info/LICENSE
dframcy-0.1.6.dist-info/METADATA
dframcy-0.1.6.dist-info/WHEEL
dframcy-0.1.6.dist-info/entry_points.txt
dframcy-0.1.6.dist-info/top_level.txt
dframcy-0.1.6.dist-info/RECORD
