Metadata-Version: 2.1
Name: dframcy
Version: 0.1.6
Summary: Pandas Dataframe integration for spaCy
Home-page: https://github.com/yash1994/dframcy
Author: Yash Patadia
Author-email: yash@patadia.org
License: UNKNOWN
Keywords: spacy,dataframe,pandas
Platform: UNKNOWN
Classifier: Development Status :: 3 - Alpha
Classifier: Intended Audience :: Developers
Classifier: Topic :: Software Development :: Build Tools
Classifier: License :: OSI Approved :: MIT License
Classifier: Programming Language :: Python :: 3.6
Requires-Dist: click
Requires-Dist: pandas
Requires-Dist: pytest
Requires-Dist: pytest-cov
Requires-Dist: spacy (>=3.0.0)
Requires-Dist: tox
Requires-Dist: tox-travis
Requires-Dist: wasabi
Requires-Dist: xlrd
